rekor_monitor_jacksonqu/__init__.py
rekor_monitor_jacksonqu/main.py
rekor_monitor_jacksonqu/merkle_proof.py
rekor_monitor_jacksonqu/util.py
rekor_monitor_jacksonqu-4.0.1.dist-info/LICENSE
rekor_monitor_jacksonqu-4.0.1.dist-info/METADATA
rekor_monitor_jacksonqu-4.0.1.dist-info/WHEEL
rekor_monitor_jacksonqu-4.0.1.dist-info/entry_points.txt
rekor_monitor_jacksonqu-4.0.1.dist-info/RECORD
